computer_use_qa_mcp/__init__.py
computer_use_qa_mcp/loop.py
computer_use_qa_mcp/server.py
computer_use_qa_mcp/tools/__init__.py
computer_use_qa_mcp/tools/base.py
computer_use_qa_mcp/tools/bash.py
computer_use_qa_mcp/tools/collection.py
computer_use_qa_mcp/tools/computer.py
computer_use_qa_mcp/tools/edit.py
computer_use_qa_mcp/tools/overlay.py
computer_use_qa_mcp/tools/run.py
computer_use_qa_mcp-0.1.2.dist-info/METADATA
computer_use_qa_mcp-0.1.2.dist-info/WHEEL
computer_use_qa_mcp-0.1.2.dist-info/entry_points.txt
computer_use_qa_mcp-0.1.2.dist-info/licenses/LICENSE
computer_use_qa_mcp-0.1.2.dist-info/RECORD
