Metadata-Version: 2.4
Name: computer-use-qa-mcp
Version: 0.1.2
Summary: MCP server for computer use quality assurance using Claude
Project-URL: Homepage, https://github.com/yourusername/computer-use-qa-mcp
Project-URL: Repository, https://github.com/yourusername/computer-use-qa-mcp
Author-email: Your Name <your.email@example.com>
License: MIT License
License-File: LICENSE
Classifier: Development Status :: 3 - Alpha
Classifier: Intended Audience :: Developers
Classifier: License :: OSI Approved :: MIT License
Classifier: Programming Language :: Python :: 3
Classifier: Programming Language :: Python :: 3.11
Classifier: Programming Language :: Python :: 3.12
Classifier: Programming Language :: Python :: 3.13
Requires-Python: >=3.11
Requires-Dist: anthropic[bedrock,vertex]>=0.37.1
Requires-Dist: mcp[cli]>=1.12.2
Requires-Dist: pillow>=11.3.0
Requires-Dist: pyautogui>=0.9.54
